README.rst
setup.py
cratesmirror/__init__.py
cratesmirror/__main__.py
cratesmirror/_mirror.py
cratesmirror/_tpool.py
cratesmirror/_utils.py
cratesmirror.egg-info/PKG-INFO
cratesmirror.egg-info/SOURCES.txt
cratesmirror.egg-info/dependency_links.txt
cratesmirror.egg-info/entry_points.txt
cratesmirror.egg-info/not-zip-safe
cratesmirror.egg-info/requires.txt
cratesmirror.egg-info/top_level.txt